{
  "AGRO3.SA": {
    "pvp": 0.9870092,
    "dy": 0.0366,
    "evEbitda": -35.412,
    "vpa": 20.861,
    "lpa": -0.02,
    "psr": 2.1250048,
    "roe": -0.00074,
    "roa": -0.01319,
    "margemBruta": 0.043920003,
    "margemOperacional": -0.08424,
    "margemLiquida": -0.0016300001,
    "dividaPL": 63.663,
    "liquidezCorrente": 1.609
  },
  "AMOB3.SA": {
    "pvp": 0.1556109,
    "vpa": 76.28,
    "lpa": -7.54,
    "margemBruta": 0,
    "margemOperacional": 0,
    "margemLiquida": 0
  },
  "BBAS3.SA": {
    "pl": 9.441667,
    "pvp": 0.7037485,
    "dy": 0.0124,
    "vpa": 32.199,
    "lpa": 2.4,
    "psr": 1.7512071,
    "roe": 0.1106,
    "roa": 0.00865,
    "margemBruta": 0,
    "margemOperacional": 0.18375,
    "margemLiquida": 0.24109
  },
  "BBDC3.SA": {
    "pl": 7.6197176,
    "pvp": 0.96217686,
    "dy": 0.0128,
    "vpa": 16.868,
    "lpa": 2.13,
    "psr": 2.0823317,
    "roe": 0.13754,
    "roa": 0.010880001,
    "margemBruta": 0,
    "margemOperacional": 0.2481,
    "margemLiquida": 0.26519
  },
  "BBSE3.SA": {
    "pl": 7.3978496,
    "pvp": 6.431109,
    "dy": 0.1516,
    "evEbitda": 5.746,
    "vpa": 5.349,
    "lpa": 4.65,
    "psr": 6.4610353,
    "roe": 0.89815,
    "roa": 0.27602,
    "margemBruta": 0.98234004,
    "margemOperacional": 0.93563,
    "margemLiquida": 0.87246,
    "liquidezCorrente": 1.278
  },
  "BRSR6.SA": {
    "pl": 3.9952266,
    "pvp": 0.59732383,
    "dy": 0.0643,
    "vpa": 28.025,
    "lpa": 4.19,
    "psr": 0.9183285,
    "roe": 0.1567,
    "roa": 0.011,
    "margemBruta": 0,
    "margemOperacional": 0.44894,
    "margemLiquida": 0.2299
  },
  "B3SA3.SA": {
    "pl": 20.73494,
    "pvp": 4.9682446,
    "dy": 0.0352,
    "evEbitda": 12.915,
    "vpa": 3.464,
    "lpa": 0.83,
    "psr": 8.565033,
    "roe": 0.25591,
    "roa": 0.08862001,
    "margemBruta": 0.95489,
    "margemOperacional": 0.65740997,
    "margemLiquida": 0.45544997,
    "dividaPL": 88.134,
    "liquidezCorrente": 1.908
  },
  "CMIG3.SA": {
    "pl": 9.719298,
    "pvp": 1.6638303,
    "dy": 0.1201,
    "evEbitda": 8.259,
    "vpa": 9.989,
    "lpa": 1.71,
    "psr": 1.1121196,
    "roe": 0.1751,
    "roa": 0.06287,
    "margemBruta": 0.12495,
    "margemOperacional": 0.20073,
    "margemLiquida": 0.11456,
    "dividaPL": 69.564,
    "liquidezCorrente": 1.001
  },
  "CXSE3.SA": {
    "pl": 12.181819,
    "pvp": 3.8565419,
    "dy": 0.0753,
    "evEbitda": 10.914,
    "vpa": 4.517,
    "lpa": 1.43,
    "psr": 9.108863,
    "roe": 0.32463002,
    "roa": 0.2018,
    "margemBruta": 0.89219004,
    "margemOperacional": 0.80120003,
    "margemLiquida": 0.74801004,
    "dividaPL": 0.011,
    "liquidezCorrente": 1.702
  },
  "EGIE3.SA": {
    "pl": 13.955752,
    "pvp": 2.8241403,
    "dy": 0.0581,
    "evEbitda": 9.202,
    "vpa": 11.168,
    "lpa": 2.26,
    "psr": 2.8017251,
    "roe": 0.2182,
    "roa": 0.06559,
    "margemBruta": 0.46707,
    "margemOperacional": 0.38505,
    "margemLiquida": 0.20084,
    "dividaPL": 214.196,
    "liquidezCorrente": 1.122
  },
  "EQTL3.SA": {
    "pl": 40.708336,
    "pvp": 1.7175758,
    "dy": 0.060700003,
    "evEbitda": 9.165,
    "vpa": 22.753,
    "lpa": 0.96,
    "psr": 0.94427097,
    "roe": 0.06486,
    "margemBruta": 0.34162998,
    "margemOperacional": 0.08656,
    "margemLiquida": 0.03222,
    "dividaPL": 193.509
  },
  "ETHE11.SA": {
    "margemBruta": 0,
    "margemOperacional": 0,
    "margemLiquida": 0
  },
  "EZTC3.SA": {
    "pl": 7.0793653,
    "pvp": 0.7377185,
    "dy": 0.0913,
    "evEbitda": 10.221,
    "vpa": 18.137,
    "lpa": 1.89,
    "psr": 2.4762514,
    "roe": 0.10949001,
    "roa": 0.03442,
    "margemBruta": 0.41674998,
    "margemOperacional": 0.24354,
    "margemLiquida": 0.35694999,
    "dividaPL": 33.729,
    "liquidezCorrente": 8.329
  },
  "FLRY3.SA": {
    "pl": 13.75,
    "pvp": 1.6781082,
    "dy": 0.122700006,
    "evEbitda": 6.317,
    "vpa": 9.177,
    "lpa": 1.12,
    "psr": 1.0139984,
    "roe": 0.113970004,
    "roa": 0.0596,
    "margemBruta": 0.26607,
    "margemOperacional": 0.1094,
    "margemLiquida": 0.07391,
    "dividaPL": 103.437,
    "liquidezCorrente": 1.969
  },
  "GMAT3.SA": {
    "pl": 5.5243907,
    "pvp": 0.9792478,
    "dy": 0.055,
    "evEbitda": 6.18,
    "vpa": 4.626,
    "lpa": 0.82,
    "psr": 0.27116144,
    "roe": 0.17333001,
    "roa": 0.06525,
    "margemBruta": 0.22399999,
    "margemOperacional": 0.04298,
    "margemLiquida": 0.0477,
    "dividaPL": 59.125,
    "liquidezCorrente": 1.748
  },
  "GOLD11.SA": {
    "margemBruta": 0,
    "margemOperacional": 0,
    "margemLiquida": 0
  },
  "ITSA4.SA": {
    "pl": 8.959459,
    "pvp": 1.6748769,
    "dy": 0.0073,
    "evEbitda": 103.249,
    "vpa": 7.917,
    "lpa": 1.48,
    "psr": 18.021877,
    "roe": 0.17571,
    "roa": 0.00201,
    "margemBruta": 0.24367,
    "margemOperacional": 0.07916,
    "margemLiquida": 1.9986701,
    "dividaPL": 13.015,
    "liquidezCorrente": 3.179
  },
  "KEPL3.SA": {
    "pl": 9.111111,
    "pvp": 1.8356838,
    "dy": 0.065799996,
    "evEbitda": 6.446,
    "vpa": 4.467,
    "lpa": 0.9,
    "psr": 0.9537148,
    "roe": 0.20629999,
    "roa": 0.07988,
    "margemBruta": 0.23753001,
    "margemOperacional": 0.15231,
    "margemLiquida": 0.10486,
    "dividaPL": 43.031,
    "liquidezCorrente": 1.956
  },
  "KLBN3.SA": {
    "pl": 16.695652,
    "pvp": 0.59747934,
    "dy": 0.085200004,
    "evEbitda": 5.353,
    "vpa": 6.427,
    "lpa": 0.23,
    "psr": 1.1397525,
    "roe": 0.14569001,
    "roa": 0.025929999,
    "margemBruta": 0.27287,
    "margemOperacional": 0.07498,
    "margemLiquida": 0.06779,
    "dividaPL": 267.053,
    "liquidezCorrente": 2.059
  },
  "LEVE3.SA": {
    "pl": 7.619154,
    "pvp": 5.3823156,
    "dy": 0.0833,
    "evEbitda": 6.066,
    "vpa": 6.356,
    "lpa": 4.49,
    "psr": 0.85760343,
    "roe": 0.74492997,
    "roa": 0.14077,
    "margemBruta": 0.27048,
    "margemOperacional": 0.13245,
    "margemLiquida": 0.11257,
    "dividaPL": 196.887,
    "liquidezCorrente": 1.266
  },
  "MBRF3.SA": {
    "pl": 60.638885,
    "pvp": 2.7168639,
    "dy": 0.2586,
    "evEbitda": 7.434,
    "vpa": 8.035,
    "lpa": 0.36,
    "psr": 0.1866511,
    "roe": 0.04453,
    "roa": 0.02489,
    "margemBruta": 0.123100005,
    "margemOperacional": 0.0361,
    "margemLiquida": 0.0021799998,
    "dividaPL": 529.705,
    "liquidezCorrente": 1.078
  },
  "PETR3.SA": {
    "pl": 6.6462665,
    "pvp": 1.683199,
    "dy": 0.072,
    "evEbitda": 4.973,
    "vpa": 32.26,
    "lpa": 8.17,
    "psr": 1.4066116,
    "roe": 0.28176,
    "roa": 0.08613,
    "margemBruta": 0.47632998,
    "margemOperacional": 0.26850998,
    "margemLiquida": 0.22134,
    "dividaPL": 91.963,
    "liquidezCorrente": 0.706
  },
  "PRIO3.SA": {
    "pl": 25.566788,
    "pvp": 2.224945,
    "evEbitda": 10.26,
    "vpa": 31.83,
    "lpa": 2.77,
    "psr": 3.6801295,
    "roe": 0.08708999,
    "roa": 0.022669999,
    "margemBruta": 0.19917,
    "margemOperacional": 0.098859996,
    "margemLiquida": 0.14446999,
    "dividaPL": 110.312,
    "liquidezCorrente": 1.819
  },
  "PSSA3.SA": {
    "pl": 9.353167,
    "pvp": 1.9823447,
    "dy": 0.0513,
    "evEbitda": 3.781,
    "vpa": 24.582,
    "lpa": 5.21,
    "psr": 0.72288936,
    "roe": 0.22815001,
    "roa": 0.06106,
    "margemBruta": 0.40445998,
    "margemOperacional": 0.09952,
    "margemLiquida": 0.07808,
    "dividaPL": 4.536,
    "liquidezCorrente": 1.218
  },
  "QBTC11.SA": {
    "margemBruta": 0,
    "margemOperacional": 0,
    "margemLiquida": 0
  },
  "QSOL11.SA": {
    "margemBruta": 0,
    "margemOperacional": 0,
    "margemLiquida": 0
  },
  "RAIZ4.SA": {
    "evEbitda": 103.916,
    "vpa": -0.154,
    "lpa": -2.15,
    "psr": 0.022712877,
    "roe": -2.31277,
    "roa": -0.03151,
    "margemBruta": 0.03964,
    "margemOperacional": -0.10459,
    "margemLiquida": -0.09583,
    "liquidezCorrente": 1.691
  },
  "RANI3.SA": {
    "pl": 8.563636,
    "pvp": 1.4954755,
    "dy": 0.048299998,
    "evEbitda": 6.349,
    "vpa": 6.299,
    "lpa": 1.1,
    "psr": 1.2876163,
    "roe": 0.18021,
    "roa": 0.054759998,
    "margemBruta": 0.34599,
    "margemOperacional": 0.16437,
    "margemLiquida": 0.14354,
    "dividaPL": 135.124,
    "liquidezCorrente": 2.773
  },
  "SAPR4.SA": {
    "pl": 6.341086,
    "pvp": 0.2002252,
    "dy": 0.0275,
    "evEbitda": 1.88,
    "vpa": 40.854,
    "lpa": 1.29,
    "psr": 1.7155328,
    "roe": 0.17944999,
    "roa": 0.04665,
    "margemBruta": 0.56273997,
    "margemOperacional": 0.28479,
    "margemLiquida": 0.2886,
    "dividaPL": 59.87,
    "liquidezCorrente": 1.199
  },
  "SBFG3.SA": {
    "pl": 8.307143,
    "pvp": 0.8209219,
    "dy": 0.0467,
    "evEbitda": 7.304,
    "vpa": 14.167,
    "lpa": 1.4,
    "psr": 0.34615397,
    "roe": 0.10802,
    "roa": 0.03584,
    "margemBruta": 0.48279,
    "margemOperacional": 0.06848,
    "margemLiquida": 0.0424,
    "dividaPL": 96.014,
    "liquidezCorrente": 1.356
  },
  "SMTO3.SA": {
    "pl": 8.780173,
    "pvp": 0.9081992,
    "dy": 0.0448,
    "evEbitda": 5.017,
    "vpa": 22.429,
    "lpa": 2.32,
    "psr": 0.94934934,
    "roe": 0.11124,
    "roa": 0.03426,
    "margemBruta": 0.24601,
    "margemOperacional": 0.20143999,
    "margemLiquida": 0.11094,
    "dividaPL": 160.269,
    "liquidezCorrente": 2.872
  },
  "SOJA3.SA": {
    "pl": 9.121621,
    "pvp": 0.8333333,
    "dy": 0.0651,
    "evEbitda": 17.816,
    "vpa": 8.1,
    "lpa": 0.74,
    "psr": 0.36308804,
    "roe": 0.051570002,
    "roa": 0.018380001,
    "margemBruta": 0.102910005,
    "margemOperacional": 0.000080000005,
    "margemLiquida": 0.00763,
    "dividaPL": 70.522,
    "liquidezCorrente": 6.773
  },
  "SUZB3.SA": {
    "pl": 4.6660495,
    "pvp": 1.4228891,
    "dy": 0.0222,
    "evEbitda": 6.625,
    "vpa": 35.449,
    "lpa": 10.81,
    "psr": 1.2440963,
    "roe": 0.35192,
    "roa": 0.037750002,
    "margemBruta": 0.32377,
    "margemOperacional": 0.16847,
    "margemLiquida": 0.26754,
    "dividaPL": 231.459,
    "liquidezCorrente": 3.185
  },
  "TAEE11.SA": {
    "pl": 39.528847,
    "pvp": 1.8523859,
    "dy": 0.078600004,
    "evEbitda": 22.351,
    "vpa": 22.193,
    "lpa": 1.04,
    "psr": 3.062717,
    "roe": 0.21719,
    "roa": 0.066350006,
    "margemBruta": 0.55202,
    "margemOperacional": 0.4627,
    "margemLiquida": 0.34166,
    "dividaPL": 146.586,
    "liquidezCorrente": 1.566
  },
  "TTEN3.SA": {
    "pl": 9.602485,
    "pvp": 1.6448559,
    "dy": 0.0241,
    "evEbitda": 14.859,
    "vpa": 9.399,
    "lpa": 1.61,
    "psr": 0.4713396,
    "roe": 0.18494,
    "roa": 0.030650001,
    "margemBruta": 0.15127,
    "margemOperacional": 0.022249999,
    "margemLiquida": 0.04966,
    "dividaPL": 100.14,
    "liquidezCorrente": 1.356
  },
  "VAMO3.SA": {
    "pl": 12.16129,
    "pvp": 1.5546392,
    "dy": 0.0372,
    "evEbitda": 4.372,
    "vpa": 2.425,
    "lpa": 0.31,
    "psr": 0.70114136,
    "roe": 0.13136,
    "roa": 0.075500004,
    "margemBruta": 0.52428,
    "margemOperacional": 0.46729,
    "margemLiquida": 0.05711,
    "dividaPL": 651.433,
    "liquidezCorrente": 1.81
  },
  "VIVT3.SA": {
    "pl": 20.947643,
    "pvp": 1.8604976,
    "dy": 0.0577,
    "evEbitda": 7.309,
    "vpa": 21.505,
    "lpa": 1.91,
    "psr": 2.1454182,
    "roe": 0.08901,
    "roa": 0.05242,
    "margemBruta": 0.48099998,
    "margemOperacional": 0.19459,
    "margemLiquida": 0.1035,
    "dividaPL": 29.627,
    "liquidezCorrente": 0.999
  },
  "WEGE3.SA": {
    "pl": 31.19079,
    "pvp": 11.421344,
    "dy": 0.0084,
    "evEbitda": 22.608,
    "vpa": 4.151,
    "lpa": 1.52,
    "psr": 4.8749666,
    "roe": 0.32514998,
    "roa": 0.11845,
    "margemBruta": 0.3353,
    "margemOperacional": 0.19398001,
    "margemLiquida": 0.15626,
    "dividaPL": 29.31,
    "liquidezCorrente": 1.548
  },
  "GOOGL": {
    "pl": 25.378351,
    "pvp": 7.985911,
    "dy": 0.0031,
    "evEbitda": 21.7,
    "vpa": 34.353,
    "lpa": 10.81,
    "psr": 8.238318,
    "roe": 0.35705003,
    "roa": 0.15427,
    "margemBruta": 0.59652,
    "margemOperacional": 0.31568,
    "margemLiquida": 0.32810003,
    "dividaPL": 16.133,
    "liquidezCorrente": 2.005
  },
  "AMZN": {
    "pl": 27.763231,
    "pvp": 5.2038846,
    "evEbitda": 15.065,
    "vpa": 38.306,
    "lpa": 7.18,
    "psr": 2.984834,
    "roe": 0.22286,
    "roa": 0.06928,
    "margemBruta": 0.50286,
    "margemOperacional": 0.10533,
    "margemLiquida": 0.108339995,
    "dividaPL": 43.435,
    "liquidezCorrente": 1.051
  },
  "NVDA": {
    "pl": 34.11813,
    "pvp": 25.883808,
    "dy": 0.0002,
    "evEbitda": 30.17,
    "vpa": 6.472,
    "lpa": 4.91,
    "psr": 18.85529,
    "roe": 1.01485,
    "roa": 0.51188,
    "margemBruta": 0.71068,
    "margemOperacional": 0.65024,
    "margemLiquida": 0.55603004,
    "dividaPL": 7.255,
    "liquidezCorrente": 3.905
  },
  "TSM": {
    "pl": 31.53861,
    "pvp": 49.96769,
    "dy": 0.0108,
    "evEbitda": 2.492,
    "vpa": 6.5390253,
    "lpa": 10.36,
    "psr": 0.44489744,
    "roe": 0.35064,
    "roa": 0.16555001,
    "margemBruta": 0.59891,
    "margemOperacional": 0.53916,
    "margemLiquida": 0.45099998,
    "dividaPL": 19.565,
    "liquidezCorrente": 2.618
  },
  "ASML": {
    "pl": 45.66865,
    "pvp": 22.174341,
    "dy": 0.0068,
    "evEbitda": 40.221,
    "vpa": 58.73771,
    "lpa": 28.52,
    "psr": 15.655599,
    "roe": 0.50458,
    "roa": 0.14247,
    "margemBruta": 0.52830005,
    "margemOperacional": 0.35304,
    "margemLiquida": 0.29416,
    "dividaPL": 23.916,
    "liquidezCorrente": 1.262
  },
  "AVGO": {
    "pl": 58.498055,
    "pvp": 5.077253,
    "dy": 0.0086,
    "evEbitda": 4.11,
    "vpa": 59.221,
    "lpa": 5.14,
    "psr": 20.878212,
    "roe": 0.33370999,
    "roa": 0.10663,
    "margemBruta": 0.76725996,
    "margemOperacional": 0.31765,
    "margemLiquida": 0.36571997,
    "dividaPL": 166.032,
    "liquidezCorrente": 1.902
  },
  "IRS": {
    "pl": 3.512761,
    "pvp": 8.610641,
    "dy": 0.1584,
    "evEbitda": 3.845,
    "vpa": 1.7582897,
    "lpa": 4.31,
    "psr": 0.0025451176,
    "roe": 0.31178,
    "roa": 0.038680002,
    "margemBruta": 0.61626,
    "margemOperacional": 0.54974,
    "margemLiquida": 0.98941004,
    "dividaPL": 50.658,
    "liquidezCorrente": 1.49
  },
  "TSLA": {
    "pl": 331.9541,
    "pvp": 16.524181,
    "evEbitda": 126.548,
    "vpa": 21.897,
    "lpa": 1.09,
    "psr": 14.318098,
    "roe": 0.049250003,
    "roa": 0.02095,
    "margemBruta": 0.18027,
    "margemOperacional": 0.047030002,
    "margemLiquida": 0.040009998,
    "dividaPL": 17.763,
    "liquidezCorrente": 2.164
  },
  "MU": {
    "pl": 16.865911,
    "pvp": 5.56097,
    "dy": 0.0017,
    "evEbitda": 10.843,
    "vpa": 64.237,
    "lpa": 21.18,
    "psr": 6.931453,
    "roe": 0.39823002,
    "roa": 0.20145,
    "margemBruta": 0.58437,
    "margemOperacional": 0.67624,
    "margemLiquida": 0.41486,
    "dividaPL": 14.902,
    "liquidezCorrente": 2.897
  },
  "VZ": {
    "pl": 12.391626,
    "pvp": 2.031086,
    "dy": 0.0563,
    "evEbitda": 7.585,
    "vpa": 24.77,
    "lpa": 4.06,
    "psr": 1.5354959,
    "roe": 0.17069,
    "roa": 0.05014,
    "margemBruta": 0.59071,
    "margemOperacional": 0.20989001,
    "margemLiquida": 0.124280006,
    "dividaPL": 174.78,
    "liquidezCorrente": 0.913
  },
  "T": {
    "pl": 9.572369,
    "pvp": 1.8527951,
    "dy": 0.0381,
    "evEbitda": 8.205,
    "vpa": 15.706,
    "lpa": 3.04,
    "psr": 1.6213293,
    "roe": 0.18805,
    "roa": 0.040749997,
    "margemBruta": 0.59554,
    "margemOperacional": 0.18416001,
    "margemLiquida": 0.17472,
    "dividaPL": 124.179,
    "liquidezCorrente": 0.906
  },
  "HD": {
    "pl": 22.619549,
    "pvp": 25.003885,
    "dy": 0.029000001,
    "evEbitda": 15.389,
    "vpa": 12.864,
    "lpa": 14.22,
    "psr": 1.945356,
    "roe": 1.45541,
    "roa": 0.12977,
    "margemBruta": 0.33316,
    "margemOperacional": 0.100760005,
    "margemLiquida": 0.08596,
    "dividaPL": 514.392,
    "liquidezCorrente": 1.061
  },
  "SHOP": {
    "pl": 118.98936,
    "pvp": 10.824542,
    "evEbitda": 72.683,
    "vpa": 10.333,
    "lpa": 0.94,
    "psr": 12.631845,
    "roe": 0.09836,
    "roa": 0.08149,
    "margemBruta": 0.4807,
    "margemOperacional": 0.20289,
    "margemLiquida": 0.106520005,
    "dividaPL": 1.395,
    "liquidezCorrente": 5.96
  },
  "DIS": {
    "pl": 13.611193,
    "pvp": 1.5131223,
    "dy": 0.0162,
    "evEbitda": 10.889,
    "vpa": 61.079,
    "lpa": 6.79,
    "psr": 1.7123201,
    "roe": 0.12024,
    "roa": 0.04366,
    "margemBruta": 0.37284002,
    "margemOperacional": 0.15361,
    "margemLiquida": 0.128,
    "dividaPL": 40.909,
    "liquidezCorrente": 0.669
  },
  "SPG": {
    "pl": 12.725283,
    "pvp": 11.339836,
    "dy": 0.048,
    "evEbitda": 18.809,
    "vpa": 15.89,
    "lpa": 14.16,
    "psr": 9.199982,
    "roe": 1.04109,
    "roa": 0.05436,
    "margemBruta": 0.81899,
    "margemOperacional": 0.49717,
    "margemLiquida": 0.7271,
    "dividaPL": 435.463,
    "liquidezCorrente": 0.236
  },
  "ANET": {
    "pl": 43.916363,
    "pvp": 12.26714,
    "evEbitda": 35.915,
    "vpa": 9.845,
    "lpa": 2.75,
    "psr": 16.88751,
    "roe": 0.314,
    "roa": 0.14392,
    "margemBruta": 0.64056,
    "margemOperacional": 0.41519,
    "margemLiquida": 0.38991,
    "dividaPL": 0.732,
    "liquidezCorrente": 3.048
  },
  "ICE": {
    "pl": 26.459272,
    "pvp": 2.9937642,
    "dy": 0.0136,
    "evEbitda": 17.205,
    "vpa": 50.996,
    "lpa": 5.77,
    "psr": 8.765397,
    "roe": 0.11885,
    "roa": 0.022550002,
    "margemBruta": 1,
    "margemOperacional": 0.49561,
    "margemLiquida": 0.33380002,
    "dividaPL": 70.077,
    "liquidezCorrente": 1.02
  },
  "KO": {
    "pl": 24.904606,
    "pvp": 10.124365,
    "dy": 0.0272,
    "evEbitda": 22.38,
    "vpa": 7.478,
    "lpa": 3.04,
    "psr": 6.79726,
    "roe": 0.43323,
    "roa": 0.09147,
    "margemBruta": 0.61626,
    "margemOperacional": 0.24656999,
    "margemLiquida": 0.2734,
    "dividaPL": 139.793,
    "liquidezCorrente": 1.459
  },
  "EQNR": {
    "pl": 21.407215,
    "pvp": 2.568654,
    "dy": 0.0376,
    "evEbitda": 3.265,
    "vpa": 16.168,
    "lpa": 1.94,
    "psr": 0.9767723,
    "roe": 0.12206,
    "roa": 0.12642999,
    "margemBruta": 0.3703,
    "margemOperacional": 0.21440001,
    "margemLiquida": 0.04758,
    "dividaPL": 77.093,
    "liquidezCorrente": 1.265
  },
  "EPR": {
    "pl": 14.85061,
    "pvp": 1.5925066,
    "dy": 0.073,
    "evEbitda": 12.324,
    "vpa": 30.587,
    "lpa": 3.28,
    "psr": 5.2205787,
    "roe": 0.11788,
    "roa": 0.042090002,
    "margemBruta": 0.91712,
    "margemOperacional": 0.52915,
    "margemLiquida": 0.38509,
    "dividaPL": 134.214,
    "liquidezCorrente": 1.617
  },
  "WFC": {
    "pl": 12.330671,
    "pvp": 1.4511036,
    "dy": 0.0233,
    "vpa": 53.194,
    "lpa": 6.26,
    "psr": 2.9757276,
    "roe": 0.11732,
    "roa": 0.01047,
    "margemBruta": 0,
    "margemOperacional": 0.29938,
    "margemLiquida": 0.26659
  },
  "VICI": {
    "pl": 10.195403,
    "pvp": 1.0231467,
    "dy": 0.067,
    "evEbitda": 12.596,
    "vpa": 26.008,
    "lpa": 2.61,
    "psr": 7.1005926,
    "roe": 0.10217,
    "roa": 0.049510002,
    "margemBruta": 0.9914,
    "margemOperacional": 0.8031,
    "margemLiquida": 0.69281,
    "dividaPL": 62.679,
    "liquidezCorrente": 17.233
  },
  "O": {
    "pl": 51.871796,
    "pvp": 1.437232,
    "dy": 0.0533,
    "evEbitda": 16.882,
    "vpa": 42.227,
    "lpa": 1.17,
    "psr": 9.820111,
    "roe": 0.02702,
    "roa": 0.02269,
    "margemBruta": 0.92559,
    "margemOperacional": 0.46975,
    "margemLiquida": 0.18370001,
    "dividaPL": 73.505,
    "liquidezCorrente": 1.245
  },
  "CPRT": {
    "pl": 20.396227,
    "pvp": 3.191301,
    "evEbitda": 13.505,
    "vpa": 10.162,
    "lpa": 1.59,
    "psr": 6.80453,
    "roe": 0.17129,
    "roa": 0.109919995,
    "margemBruta": 0.47344002,
    "margemOperacional": 0.34654,
    "margemLiquida": 0.33758,
    "dividaPL": 0.98,
    "liquidezCorrente": 10.061
  },
  "ASX": {
    "pl": 38.392857,
    "pvp": 8.666084,
    "dy": 0.0166,
    "evEbitda": 2.462,
    "vpa": 2.480936,
    "lpa": 0.56,
    "psr": 0.072857685,
    "roe": 0.116359994,
    "roa": 0.03892,
    "margemBruta": 0.17694001,
    "margemOperacional": 0.099429995,
    "margemLiquida": 0.063,
    "dividaPL": 70.617,
    "liquidezCorrente": 1.284
  },
  "CEPU": {
    "pl": 8.809525,
    "pvp": 12.034005,
    "evEbitda": 0.524,
    "vpa": 1.2298483,
    "lpa": 1.68,
    "psr": 0.0020759702,
    "roe": 0.13927001,
    "roa": 0.052160002,
    "margemBruta": 0.35881,
    "margemOperacional": 0.22393999,
    "margemLiquida": 0.31561002,
    "dividaPL": 18.846,
    "liquidezCorrente": 1.773
  },
  "NVO": {
    "pl": 10.123596,
    "pvp": 5.34791,
    "dy": 0.051599998,
    "evEbitda": 1.723,
    "vpa": 6.7390814,
    "lpa": 3.56,
    "psr": 0.52161676,
    "roe": 0.60696,
    "roa": 0.17429,
    "margemBruta": 0.82405996,
    "margemOperacional": 0.44528,
    "margemLiquida": 0.33143002,
    "dividaPL": 67.488,
    "liquidezCorrente": 0.8
  },
  "PLTR": {
    "pl": 227.07936,
    "pvp": 46.31272,
    "evEbitda": 232.826,
    "vpa": 3.089,
    "lpa": 0.63,
    "psr": 76.45118,
    "roe": 0.25983,
    "roa": 0.11597,
    "margemBruta": 0.82366997,
    "margemOperacional": 0.40901002,
    "margemLiquida": 0.36310002,
    "dividaPL": 3.063,
    "liquidezCorrente": 7.11
  },
  "JBL": {
    "pl": 35.18868,
    "pvp": 20.593107,
    "dy": 0.0011999999,
    "evEbitda": 12.722,
    "vpa": 12.679,
    "lpa": 7.42,
    "psr": 0.853812,
    "roe": 0.59696996,
    "roa": 0.053489998,
    "margemBruta": 0.09037,
    "margemOperacional": 0.046729997,
    "margemLiquida": 0.02477,
    "dividaPL": 325.352,
    "liquidezCorrente": 1.013
  },
  "QCOM": {
    "pl": 25.627016,
    "pvp": 5.9167714,
    "dy": 0.027999999,
    "evEbitda": 10.071,
    "vpa": 21.483,
    "lpa": 4.96,
    "psr": 3.0258145,
    "roe": 0.2148,
    "roa": 0.14047,
    "margemBruta": 0.55101,
    "margemOperacional": 0.27473,
    "margemLiquida": 0.11958,
    "dividaPL": 64.218,
    "liquidezCorrente": 2.505
  },
  "AAPL": {
    "pl": 31.453857,
    "pvp": 41.48049,
    "dy": 0.0042,
    "evEbitda": 24.043,
    "vpa": 5.998,
    "lpa": 7.91,
    "psr": 8.394631,
    "roe": 1.5202099,
    "roa": 0.24377,
    "margemBruta": 0.47325,
    "margemOperacional": 0.35374,
    "margemLiquida": 0.27037,
    "dividaPL": 102.63,
    "liquidezCorrente": 0.974
  },
  "MSFT": {
    "pl": 22.326033,
    "pvp": 6.7807655,
    "dy": 0.010199999,
    "evEbitda": 15.309,
    "vpa": 52.615,
    "lpa": 15.98,
    "psr": 8.681039,
    "roe": 0.34390998,
    "roa": 0.1486,
    "margemBruta": 0.68586,
    "margemOperacional": 0.47094002,
    "margemLiquida": 0.39044,
    "dividaPL": 31.539,
    "liquidezCorrente": 1.386
  },
  "BAC": {
    "pl": 12.328085,
    "pvp": 1.2218724,
    "dy": 0.0238,
    "vpa": 38.441,
    "lpa": 3.81,
    "psr": 3.1379864,
    "roe": 0.10217,
    "roa": 0.00914,
    "margemBruta": 0,
    "margemOperacional": 0.41627997,
    "margemLiquida": 0.28401
  },
  "ORCL": {
    "pl": 25.073608,
    "pvp": 11.971541,
    "dy": 0.0143,
    "evEbitda": 19.322,
    "vpa": 11.666,
    "lpa": 5.57,
    "psr": 6.2686276,
    "roe": 0.57572,
    "roa": 0.06335,
    "margemBruta": 0.67084,
    "margemOperacional": 0.32676,
    "margemLiquida": 0.25298,
    "dividaPL": 415.265,
    "liquidezCorrente": 1.347
  },
  "EQT": {
    "pl": 20.407856,
    "pvp": 1.7747827,
    "dy": 0.0098,
    "evEbitda": 8.797,
    "vpa": 38.061,
    "lpa": 3.31,
    "psr": 5.154768,
    "roe": 0.09007,
    "roa": 0.053460002,
    "margemBruta": 0.78629,
    "margemOperacional": 0.5499,
    "margemLiquida": 0.24927,
    "dividaPL": 28.932,
    "liquidezCorrente": 0.763
  },
  "MNST": {
    "pl": 37.025772,
    "pvp": 8.511672,
    "evEbitda": 25.417,
    "vpa": 8.439,
    "lpa": 1.94,
    "psr": 8.471942,
    "roe": 0.26815,
    "roa": 0.17958,
    "margemBruta": 0.55848,
    "margemOperacional": 0.31315002,
    "margemLiquida": 0.22973,
    "dividaPL": 0.8,
    "liquidezCorrente": 3.703
  },
  "CVS": {
    "pl": 50.417267,
    "pvp": 1.1842439,
    "dy": 0.038,
    "evEbitda": 10.85,
    "vpa": 59.177,
    "lpa": 1.39,
    "psr": 0.22298393,
    "roe": 0.022869999,
    "roa": 0.02471,
    "margemBruta": 0.13288,
    "margemOperacional": 0.01572,
    "margemLiquida": 0.00442,
    "dividaPL": 106.06,
    "liquidezCorrente": 0.842
  },
  "HUYA": {
    "pvp": 0.9693159,
    "evEbitda": 36.134,
    "vpa": 3.1052828,
    "lpa": -0.07,
    "psr": 0.1034749,
    "roe": -0.01806,
    "roa": -0.01249,
    "margemBruta": 0.13412,
    "margemOperacional": -0.03731,
    "margemLiquida": -0.01732,
    "dividaPL": 0.422,
    "liquidezCorrente": 2.838
  },
  "GPC": {
    "pl": 223.44681,
    "pvp": 3.2675793,
    "dy": 0.0405,
    "evEbitda": 10.388,
    "vpa": 32.14,
    "lpa": 0.47,
    "psr": 0.60125595,
    "roe": 0.015,
    "roa": 0.046040002,
    "margemBruta": 0.37452,
    "margemOperacional": 0.04851,
    "margemLiquida": 0.00271,
    "dividaPL": 156.063,
    "liquidezCorrente": 1.079
  },
  "PFE": {
    "pl": 19.882353,
    "pvp": 1.7778947,
    "dy": 0.0636,
    "evEbitda": 8.092,
    "vpa": 15.209,
    "lpa": 1.36,
    "psr": 2.4579036,
    "roe": 0.08886,
    "roa": 0.05683,
    "margemBruta": 0.75807,
    "margemOperacional": 0.23945,
    "margemLiquida": 0.124180004,
    "dividaPL": 77.957,
    "liquidezCorrente": 1.16
  },
  "ROKU": {
    "pl": 147.71187,
    "pvp": 4.8478613,
    "evEbitda": 39.739,
    "vpa": 17.977,
    "lpa": 0.59,
    "psr": 2.7121913,
    "roe": 0.03431,
    "roa": -0.000040000003,
    "margemBruta": 0.4379,
    "margemOperacional": 0.045440003,
    "margemLiquida": 0.01865,
    "dividaPL": 19.689,
    "liquidezCorrente": 2.749
  },
  "DIBS": {
    "pvp": 2.0826771,
    "evEbitda": -6.424,
    "vpa": 2.54,
    "lpa": -0.38,
    "psr": 2.1475222,
    "roe": -0.1417,
    "roa": -0.081709996,
    "margemBruta": 0.73017,
    "margemOperacional": -0.100530006,
    "margemLiquida": -0.15248999,
    "dividaPL": 19.863,
    "liquidezCorrente": 4.195
  },
  "LEG": {
    "pl": 5.6686387,
    "pvp": 1.2700516,
    "dy": 0.0209,
    "evEbitda": 6.476,
    "vpa": 7.543,
    "lpa": 1.69,
    "psr": 0.32100502,
    "roe": 0.27487,
    "roa": 0.042579997,
    "margemBruta": 0.18439,
    "margemOperacional": 0.046669997,
    "margemLiquida": 0.05805,
    "dividaPL": 161.93,
    "liquidezCorrente": 2.25
  },
  "MBUU": {
    "pl": 35.243244,
    "pvp": 0.9799722,
    "evEbitda": 7.728,
    "vpa": 26.613,
    "lpa": 0.74,
    "psr": 0.61220396,
    "roe": 0.029089998,
    "roa": 0.02012,
    "margemBruta": 0.16057,
    "margemOperacional": -0.016139999,
    "margemLiquida": 0.01758,
    "dividaPL": 5.239,
    "liquidezCorrente": 1.559
  },
  "FVRR": {
    "pl": 17.428572,
    "pvp": 0.8550903,
    "evEbitda": 2.261,
    "vpa": 11.414,
    "lpa": 0.56,
    "psr": 0.8142766,
    "roe": 0.054180004,
    "roa": 0.012259999,
    "margemBruta": 0.8157,
    "margemOperacional": 0.049569998,
    "margemLiquida": 0.04869,
    "dividaPL": 1.01,
    "liquidezCorrente": 1.931
  }
}